coverage_universe/__init__.py
coverage_universe/atoms.py
coverage_universe/cli.py
coverage_universe/coverage_engine.py
coverage_universe/report.py
coverage_universe/udl.py
coverage_universe/validate.py
coverage_universe/schemas/run.schema.json
coverage_universe/schemas/udl.schema.json
coverage_universe-0.1.8.dist-info/licenses/LICENSE
coverage_universe-0.1.8.dist-info/METADATA
coverage_universe-0.1.8.dist-info/WHEEL
coverage_universe-0.1.8.dist-info/entry_points.txt
coverage_universe-0.1.8.dist-info/top_level.txt
coverage_universe-0.1.8.dist-info/RECORD
