Metadata-Version: 2.4
Name: coverage-universe
Version: 0.1.8
Summary: Compute and report coverage over a modeled test universe
Author: Coverage Universe
License: Apache-2.0
Project-URL: Homepage, https://example.invalid/coverage-universe
Classifier: License :: OSI Approved :: Apache Software License
Classifier: Programming Language :: Python
Classifier: Programming Language :: Python :: 3
Requires-Python: >=3.8
License-File: LICENSE
Provides-Extra: validate
Requires-Dist: jsonschema>=4; extra == "validate"
Dynamic: license-file
